src/__init__.py
src/__main__.py
src/claude_integration.py
src/vibeteam_core/__init__.py
src/vibeteam_core/communication.py
src/vibeteam_core/tool_detection.py
src/vibeteam_core/adapters/__init__.py
src/vibeteam_core/adapters/base.py
src/vibeteam_core/adapters/mcp.py
src/vibeteam_core/agents/__init__.py
src/vibeteam_core/agents/base.py
src/vibeteam_core/agents/registry.py
src/vibeteam_core/orchestrator/__init__.py
src/vibeteam_core/orchestrator/core.py
src/vibeteam_core/orchestrator/project_analyzer.py
src/vibeteam_core/orchestrator/query_analyzer.py
vibeteam-0.1.1.dist-info/METADATA
vibeteam-0.1.1.dist-info/WHEEL
vibeteam-0.1.1.dist-info/entry_points.txt
vibeteam-0.1.1.dist-info/licenses/LICENSE
vibeteam-0.1.1.dist-info/RECORD
