Metadata-Version: 2.4
Name: vibeteam
Version: 0.1.1
Summary: MCP server for orchestrating sub-agents based on query analysis
Project-URL: Homepage, https://github.com/XiaoConstantine/vibeteam
Project-URL: Repository, https://github.com/XiaoConstantine/vibeteam
Author-email: Xiao <constantine124@gmail.com>
Maintainer-email: Xiao <constantine124@gmail.com>
License: MIT
License-File: LICENSE
Keywords: agents,ai,claude,mcp,orchestration
Classifier: Development Status :: 3 - Alpha
Classifier: Intended Audience :: Developers
Classifier: License :: OSI Approved :: MIT License
Classifier: Programming Language :: Python :: 3
Classifier: Programming Language :: Python :: 3.10
Classifier: Programming Language :: Python :: 3.11
Classifier: Programming Language :: Python :: 3.12
Requires-Python: >=3.10
Requires-Dist: aiohttp>=3.9.0
Requires-Dist: mcp>=1.0.0
Requires-Dist: pydantic>=2.0.0
Requires-Dist: typing-extensions>=4.8.0
Provides-Extra: dev
Requires-Dist: ruff>=0.1.0; extra == 'dev'
Requires-Dist: twine>=4.0.0; extra == 'dev'
Provides-Extra: enhanced-detection
Requires-Dist: psutil>=5.0.0; extra == 'enhanced-detection'
